[
  {
    "sykmeldinger": [
      {
        "id": "cd223f13-8a79-4e25-bd28-50e88ab54be6",
        "startLegemeldtFravaer": "2018-10-09",
        "skalViseSkravertFelt": true,
        "identdato": "2018-06-24",
        "status": "NY",
        "naermesteLederStatus": null,
        "innsendtArbeidsgivernavn": null,
        "valgtArbeidssituasjon": null,
        "mottakendeArbeidsgiver": null,
        "orgnummer": null,
        "sendtdato": null,
        "sporsmal": null,
        "pasient": {
          "fnr": "110110110110",
          "fornavn": "Helen",
          "mellomnavn": "Perma",
          "etternavn": "Flood"
        },
        "arbeidsgiver": "PONTYPANDY FIRE SERVICE",
        "stillingsprosent": 100,
        "diagnose": {
          "hoveddiagnose": {
            "diagnose": "TENDINITT INA",
            "diagnosekode": "L87",
            "diagnosesystem": "ICPC-2"
          },
          "bidiagnoser": [
            {
              "diagnose": "GANGLION SENE",
              "diagnosekode": "L87",
              "diagnosesystem": "ICPC-2"
            }
          ],
          "fravaersgrunnLovfestet": null,
          "fravaerBeskrivelse": "Medising årsak i kategorien annet",
          "svangerskap": true,
          "yrkesskade": true,
          "yrkesskadeDato": "2018-06-24"
        },
        "mulighetForArbeid": {
          "perioder": [
            {
              "fom": "2018-06-24",
              "tom": "2018-08-02",
              "grad": 100,
              "behandlingsdager": null,
              "reisetilskudd": null,
              "avventende": null
            }
          ],
          "aktivitetIkkeMulig433": [
            "Annet"
          ],
          "aktivitetIkkeMulig434": [
            "Annet"
          ],
          "aarsakAktivitetIkkeMulig433": "andre årsaker til sykefravær",
          "aarsakAktivitetIkkeMulig434": "andre årsaker til sykefravær"
        },
        "friskmelding": {
          "arbeidsfoerEtterPerioden": true,
          "hensynPaaArbeidsplassen": "Må ta det pent",
          "antarReturSammeArbeidsgiver": true,
          "antattDatoReturSammeArbeidsgiver": "2018-06-24",
          "antarReturAnnenArbeidsgiver": true,
          "tilbakemeldingReturArbeid": "2018-06-24",
          "utenArbeidsgiverAntarTilbakeIArbeid": false,
          "utenArbeidsgiverAntarTilbakeIArbeidDato": null,
          "utenArbeidsgiverTilbakemelding": null
        },
        "utdypendeOpplysninger": {
          "sykehistorie": "Langvarig korsryggsmerter. Ømhet og smerte",
          "paavirkningArbeidsevne": "Kan ikke utføre arbeidsoppgaver 100% som kreves fra yrket",
          "resultatAvBehandling": "Nei",
          "henvisningUtredningBehandling": "Henvist til fysio",
          "grupper": [
            {
              "id": "6.2",
              "sporsmal": [
                {
                  "id": "6.2.1",
                  "svar": "Langvarig korsryggsmerter. Ømhet og smerte"
                },
                {
                  "id": "6.2.2",
                  "svar": "Kan ikke utføre arbeidsoppgaver 100% som kreves fra yrket"
                },
                {
                  "id": "6.2.3",
                  "svar": "Nei"
                },
                {
                  "id": "6.2.4",
                  "svar": "Henvist til fysio"
                }
              ]
            }
          ]
        },
        "arbeidsevne": {
          "tilretteleggingArbeidsplass": "Fortsett som sist.",
          "tiltakNAV": "Pasienten har plager som er kommet tilbake etter operasjon. Det er nylig tatt MR bildet som viser forandringer i hånd som mulig må opereres. Venter på time. Det er mulig sykemledingen vil vare utover aktuell sm periode. ",
          "tiltakAndre": null
        },
        "meldingTilNav": {
          "navBoerTaTakISaken": false,
          "navBoerTaTakISakenBegrunnelse": null
        },
        "innspillTilArbeidsgiver": null,
        "tilbakedatering": {
          "dokumenterbarPasientkontakt": null,
          "tilbakedatertBegrunnelse": null
        },
        "bekreftelse": {
          "utstedelsesdato": "2018-10-09",
          "sykmelder": "Helen Flood",
          "sykmelderTlf": "113"
        }
      }
    ],
    "hendelser": [],
    "oppfoelgingsdato": "2018-06-24"
  },
  {
    "sykmeldinger": [
      {
        "id": "e9abeabb-7ac8-4513-9112-aeff1ae66829",
        "startLegemeldtFravaer": "2018-10-09",
        "skalViseSkravertFelt": true,
        "identdato": "2018-08-23",
        "status": "BEKREFTET",
        "naermesteLederStatus": null,
        "innsendtArbeidsgivernavn": null,
        "valgtArbeidssituasjon": "NAERINGSDRIVENDE",
        "mottakendeArbeidsgiver": null,
        "orgnummer": null,
        "sendtdato": "2018-10-18T13:15:09",
        "sporsmal": {
          "arbeidssituasjon": "NAERINGSDRIVENDE",
          "dekningsgrad": 100,
          "harForsikring": true,
          "fravaersperioder": [],
          "harAnnetFravaer": false
        },
        "pasient": {
          "fnr": "110110110110",
          "fornavn": "Helen",
          "mellomnavn": "Perma",
          "etternavn": "Flood"
        },
        "arbeidsgiver": "PONTYPANDY FIRE SERVICE",
        "stillingsprosent": 100,
        "diagnose": {
          "hoveddiagnose": {
            "diagnose": "TENDINITT INA",
            "diagnosekode": "L87",
            "diagnosesystem": "ICPC-2"
          },
          "bidiagnoser": [
            {
              "diagnose": "GANGLION SENE",
              "diagnosekode": "L87",
              "diagnosesystem": "ICPC-2"
            }
          ],
          "fravaersgrunnLovfestet": null,
          "fravaerBeskrivelse": "Medising årsak i kategorien annet",
          "svangerskap": true,
          "yrkesskade": true,
          "yrkesskadeDato": "2018-08-23"
        },
        "mulighetForArbeid": {
          "perioder": [
            {
              "fom": "2018-08-23",
              "tom": "2018-08-27",
              "grad": 100,
              "behandlingsdager": null,
              "reisetilskudd": null,
              "avventende": null
            }
          ],
          "aktivitetIkkeMulig433": [
            "Annet"
          ],
          "aktivitetIkkeMulig434": [
            "Annet"
          ],
          "aarsakAktivitetIkkeMulig433": "andre årsaker til sykefravær",
          "aarsakAktivitetIkkeMulig434": "andre årsaker til sykefravær"
        },
        "friskmelding": {
          "arbeidsfoerEtterPerioden": true,
          "hensynPaaArbeidsplassen": "Må ta det pent",
          "antarReturSammeArbeidsgiver": true,
          "antattDatoReturSammeArbeidsgiver": "2018-08-23",
          "antarReturAnnenArbeidsgiver": true,
          "tilbakemeldingReturArbeid": "2018-08-23",
          "utenArbeidsgiverAntarTilbakeIArbeid": false,
          "utenArbeidsgiverAntarTilbakeIArbeidDato": null,
          "utenArbeidsgiverTilbakemelding": null
        },
        "utdypendeOpplysninger": {
          "sykehistorie": "Langvarig korsryggsmerter. Ømhet og smerte",
          "paavirkningArbeidsevne": "Kan ikke utføre arbeidsoppgaver 100% som kreves fra yrket",
          "resultatAvBehandling": "Nei",
          "henvisningUtredningBehandling": "Henvist til fysio",
          "grupper": [
            {
              "id": "6.2",
              "sporsmal": [
                {
                  "id": "6.2.1",
                  "svar": "Langvarig korsryggsmerter. Ømhet og smerte"
                },
                {
                  "id": "6.2.2",
                  "svar": "Kan ikke utføre arbeidsoppgaver 100% som kreves fra yrket"
                },
                {
                  "id": "6.2.3",
                  "svar": "Nei"
                },
                {
                  "id": "6.2.4",
                  "svar": "Henvist til fysio"
                }
              ]
            }
          ]
        },
        "arbeidsevne": {
          "tilretteleggingArbeidsplass": "Fortsett som sist.",
          "tiltakNAV": "Pasienten har plager som er kommet tilbake etter operasjon. Det er nylig tatt MR bildet som viser forandringer i hånd som mulig må opereres. Venter på time. Det er mulig sykemledingen vil vare utover aktuell sm periode. ",
          "tiltakAndre": null
        },
        "meldingTilNav": {
          "navBoerTaTakISaken": false,
          "navBoerTaTakISakenBegrunnelse": null
        },
        "innspillTilArbeidsgiver": null,
        "tilbakedatering": {
          "dokumenterbarPasientkontakt": null,
          "tilbakedatertBegrunnelse": null
        },
        "bekreftelse": {
          "utstedelsesdato": "2018-10-09",
          "sykmelder": "Helen Flood",
          "sykmelderTlf": "113"
        }
      },
      {
        "id": "4ee59626-fe82-4f18-835e-cb72b0697574",
        "startLegemeldtFravaer": "2018-10-09",
        "skalViseSkravertFelt": true,
        "identdato": "2018-09-05",
        "status": "SENDT",
        "naermesteLederStatus": null,
        "innsendtArbeidsgivernavn": null,
        "valgtArbeidssituasjon": null,
        "mottakendeArbeidsgiver": {
          "navn": "PONTYPANDY FIRE SERVICE",
          "virksomhetsnummer": "110110110",
          "juridiskOrgnummer": "110110110"
        },
        "orgnummer": "110110110",
        "sendtdato": "2018-10-18T13:07:34",
        "sporsmal": {
          "arbeidssituasjon": "ARBEIDSTAKER",
          "dekningsgrad": null,
          "harForsikring": null,
          "fravaersperioder": [],
          "harAnnetFravaer": null
        },
        "pasient": {
          "fnr": "110110110110",
          "fornavn": "Helen",
          "mellomnavn": "Perma",
          "etternavn": "Flood"
        },
        "arbeidsgiver": "PONTYPANDY FIRE SERVICE",
        "stillingsprosent": 100,
        "diagnose": {
          "hoveddiagnose": {
            "diagnose": "TENDINITT INA",
            "diagnosekode": "L87",
            "diagnosesystem": "ICPC-2"
          },
          "bidiagnoser": [
            {
              "diagnose": "GANGLION SENE",
              "diagnosekode": "L87",
              "diagnosesystem": "ICPC-2"
            }
          ],
          "fravaersgrunnLovfestet": null,
          "fravaerBeskrivelse": "Medising årsak i kategorien annet",
          "svangerskap": true,
          "yrkesskade": true,
          "yrkesskadeDato": "2018-09-05"
        },
        "mulighetForArbeid": {
          "perioder": [
            {
              "fom": "2018-09-05",
              "tom": "2018-10-03",
              "grad": 100,
              "behandlingsdager": null,
              "reisetilskudd": null,
              "avventende": null
            }
          ],
          "aktivitetIkkeMulig433": [
            "Annet"
          ],
          "aktivitetIkkeMulig434": [
            "Annet"
          ],
          "aarsakAktivitetIkkeMulig433": "andre årsaker til sykefravær",
          "aarsakAktivitetIkkeMulig434": "andre årsaker til sykefravær"
        },
        "friskmelding": {
          "arbeidsfoerEtterPerioden": true,
          "hensynPaaArbeidsplassen": "Må ta det pent",
          "antarReturSammeArbeidsgiver": true,
          "antattDatoReturSammeArbeidsgiver": "2018-09-05",
          "antarReturAnnenArbeidsgiver": true,
          "tilbakemeldingReturArbeid": "2018-09-05",
          "utenArbeidsgiverAntarTilbakeIArbeid": false,
          "utenArbeidsgiverAntarTilbakeIArbeidDato": null,
          "utenArbeidsgiverTilbakemelding": null
        },
        "utdypendeOpplysninger": {
          "sykehistorie": "Langvarig korsryggsmerter. Ømhet og smerte",
          "paavirkningArbeidsevne": "Kan ikke utføre arbeidsoppgaver 100% som kreves fra yrket",
          "resultatAvBehandling": "Nei",
          "henvisningUtredningBehandling": "Henvist til fysio",
          "grupper": [
            {
              "id": "6.2",
              "sporsmal": [
                {
                  "id": "6.2.1",
                  "svar": "Langvarig korsryggsmerter. Ømhet og smerte"
                },
                {
                  "id": "6.2.2",
                  "svar": "Kan ikke utføre arbeidsoppgaver 100% som kreves fra yrket"
                },
                {
                  "id": "6.2.3",
                  "svar": "Nei"
                },
                {
                  "id": "6.2.4",
                  "svar": "Henvist til fysio"
                }
              ]
            }
          ]
        },
        "arbeidsevne": {
          "tilretteleggingArbeidsplass": "Fortsett som sist.",
          "tiltakNAV": "Pasienten har plager som er kommet tilbake etter operasjon. Det er nylig tatt MR bildet som viser forandringer i hånd som mulig må opereres. Venter på time. Det er mulig sykemledingen vil vare utover aktuell sm periode. ",
          "tiltakAndre": null
        },
        "meldingTilNav": {
          "navBoerTaTakISaken": false,
          "navBoerTaTakISakenBegrunnelse": null
        },
        "innspillTilArbeidsgiver": null,
        "tilbakedatering": {
          "dokumenterbarPasientkontakt": null,
          "tilbakedatertBegrunnelse": null
        },
        "bekreftelse": {
          "utstedelsesdato": "2018-10-09",
          "sykmelder": "Helen Flood",
          "sykmelderTlf": "113"
        }
      },
      {
        "id": "460e8015-0a06-43e9-b53d-8870fe3dd18c",
        "startLegemeldtFravaer": "2018-10-08",
        "skalViseSkravertFelt": true,
        "identdato": "2018-09-08",
        "status": "SENDT",
        "naermesteLederStatus": null,
        "innsendtArbeidsgivernavn": null,
        "valgtArbeidssituasjon": null,
        "mottakendeArbeidsgiver": {
          "navn": "PONTYPANDY FIRE SERVICE",
          "virksomhetsnummer": "110110110",
          "juridiskOrgnummer": "110110110"
        },
        "orgnummer": "110110110",
        "sendtdato": "2018-10-18T12:03:46",
        "sporsmal": {
          "arbeidssituasjon": "ARBEIDSTAKER",
          "dekningsgrad": null,
          "harForsikring": null,
          "fravaersperioder": [],
          "harAnnetFravaer": null
        },
        "pasient": {
          "fnr": "110110110110",
          "fornavn": "Helen",
          "mellomnavn": "Perma",
          "etternavn": "Flood"
        },
        "arbeidsgiver": "PONTYPANDY FIRE SERVICE",
        "stillingsprosent": 100,
        "diagnose": {
          "hoveddiagnose": {
            "diagnose": "TENDINITT INA",
            "diagnosekode": "L87",
            "diagnosesystem": "ICPC-2"
          },
          "bidiagnoser": [
            {
              "diagnose": "GANGLION SENE",
              "diagnosekode": "L87",
              "diagnosesystem": "ICPC-2"
            }
          ],
          "fravaersgrunnLovfestet": null,
          "fravaerBeskrivelse": "Medising årsak i kategorien annet",
          "svangerskap": true,
          "yrkesskade": true,
          "yrkesskadeDato": "2018-09-08"
        },
        "mulighetForArbeid": {
          "perioder": [
            {
              "fom": "2018-09-08",
              "tom": "2018-10-05",
              "grad": 100,
              "behandlingsdager": null,
              "reisetilskudd": null,
              "avventende": null
            }
          ],
          "aktivitetIkkeMulig433": [
            "Annet"
          ],
          "aktivitetIkkeMulig434": [
            "Annet"
          ],
          "aarsakAktivitetIkkeMulig433": "andre årsaker til sykefravær",
          "aarsakAktivitetIkkeMulig434": "andre årsaker til sykefravær"
        },
        "friskmelding": {
          "arbeidsfoerEtterPerioden": true,
          "hensynPaaArbeidsplassen": "Må ta det pent",
          "antarReturSammeArbeidsgiver": true,
          "antattDatoReturSammeArbeidsgiver": "2018-09-08",
          "antarReturAnnenArbeidsgiver": true,
          "tilbakemeldingReturArbeid": "2018-09-08",
          "utenArbeidsgiverAntarTilbakeIArbeid": false,
          "utenArbeidsgiverAntarTilbakeIArbeidDato": null,
          "utenArbeidsgiverTilbakemelding": null
        },
        "utdypendeOpplysninger": {
          "sykehistorie": "Langvarig korsryggsmerter. Ømhet og smerte",
          "paavirkningArbeidsevne": "Kan ikke utføre arbeidsoppgaver 100% som kreves fra yrket",
          "resultatAvBehandling": "Nei",
          "henvisningUtredningBehandling": "Henvist til fysio",
          "grupper": [
            {
              "id": "6.2",
              "sporsmal": [
                {
                  "id": "6.2.1",
                  "svar": "Langvarig korsryggsmerter. Ømhet og smerte"
                },
                {
                  "id": "6.2.2",
                  "svar": "Kan ikke utføre arbeidsoppgaver 100% som kreves fra yrket"
                },
                {
                  "id": "6.2.3",
                  "svar": "Nei"
                },
                {
                  "id": "6.2.4",
                  "svar": "Henvist til fysio"
                }
              ]
            }
          ]
        },
        "arbeidsevne": {
          "tilretteleggingArbeidsplass": "Fortsett som sist.",
          "tiltakNAV": "Pasienten har plager som er kommet tilbake etter operasjon. Det er nylig tatt MR bildet som viser forandringer i hånd som mulig må opereres. Venter på time. Det er mulig sykemledingen vil vare utover aktuell sm periode. ",
          "tiltakAndre": null
        },
        "meldingTilNav": {
          "navBoerTaTakISaken": false,
          "navBoerTaTakISakenBegrunnelse": null
        },
        "innspillTilArbeidsgiver": null,
        "tilbakedatering": {
          "dokumenterbarPasientkontakt": null,
          "tilbakedatertBegrunnelse": null
        },
        "bekreftelse": {
          "utstedelsesdato": "2018-10-08",
          "sykmelder": "Helen Flood",
          "sykmelderTlf": "113"
        }
      },
      {
        "id": "e59ca01b-9722-4df6-a52f-bd14e8531015",
        "startLegemeldtFravaer": "2018-10-09",
        "skalViseSkravertFelt": true,
        "identdato": "2018-10-01",
        "status": "AVBRUTT",
        "naermesteLederStatus": null,
        "innsendtArbeidsgivernavn": null,
        "valgtArbeidssituasjon": null,
        "mottakendeArbeidsgiver": null,
        "orgnummer": null,
        "sendtdato": "2018-10-18T13:10:23",
        "sporsmal": null,
        "pasient": {
          "fnr": "110110110110",
          "fornavn": "Helen",
          "mellomnavn": "Perma",
          "etternavn": "Flood"
        },
        "arbeidsgiver": "PONTYPANDY FIRE SERVICE",
        "stillingsprosent": 100,
        "diagnose": {
          "hoveddiagnose": {
            "diagnose": "TENDINITT INA",
            "diagnosekode": "L87",
            "diagnosesystem": "ICPC-2"
          },
          "bidiagnoser": [
            {
              "diagnose": "GANGLION SENE",
              "diagnosekode": "L87",
              "diagnosesystem": "ICPC-2"
            }
          ],
          "fravaersgrunnLovfestet": null,
          "fravaerBeskrivelse": "Medising årsak i kategorien annet",
          "svangerskap": true,
          "yrkesskade": true,
          "yrkesskadeDato": "2018-10-01"
        },
        "mulighetForArbeid": {
          "perioder": [
            {
              "fom": "2018-10-01",
              "tom": "2018-10-12",
              "grad": 100,
              "behandlingsdager": null,
              "reisetilskudd": null,
              "avventende": null
            }
          ],
          "aktivitetIkkeMulig433": [
            "Annet"
          ],
          "aktivitetIkkeMulig434": [
            "Annet"
          ],
          "aarsakAktivitetIkkeMulig433": "andre årsaker til sykefravær",
          "aarsakAktivitetIkkeMulig434": "andre årsaker til sykefravær"
        },
        "friskmelding": {
          "arbeidsfoerEtterPerioden": true,
          "hensynPaaArbeidsplassen": "Må ta det pent",
          "antarReturSammeArbeidsgiver": true,
          "antattDatoReturSammeArbeidsgiver": "2018-10-01",
          "antarReturAnnenArbeidsgiver": true,
          "tilbakemeldingReturArbeid": "2018-10-01",
          "utenArbeidsgiverAntarTilbakeIArbeid": false,
          "utenArbeidsgiverAntarTilbakeIArbeidDato": null,
          "utenArbeidsgiverTilbakemelding": null
        },
        "utdypendeOpplysninger": {
          "sykehistorie": "Langvarig korsryggsmerter. Ømhet og smerte",
          "paavirkningArbeidsevne": "Kan ikke utføre arbeidsoppgaver 100% som kreves fra yrket",
          "resultatAvBehandling": "Nei",
          "henvisningUtredningBehandling": "Henvist til fysio",
          "grupper": [
            {
              "id": "6.2",
              "sporsmal": [
                {
                  "id": "6.2.1",
                  "svar": "Langvarig korsryggsmerter. Ømhet og smerte"
                },
                {
                  "id": "6.2.2",
                  "svar": "Kan ikke utføre arbeidsoppgaver 100% som kreves fra yrket"
                },
                {
                  "id": "6.2.3",
                  "svar": "Nei"
                },
                {
                  "id": "6.2.4",
                  "svar": "Henvist til fysio"
                }
              ]
            }
          ]
        },
        "arbeidsevne": {
          "tilretteleggingArbeidsplass": "Fortsett som sist.",
          "tiltakNAV": "Pasienten har plager som er kommet tilbake etter operasjon. Det er nylig tatt MR bildet som viser forandringer i hånd som mulig må opereres. Venter på time. Det er mulig sykemledingen vil vare utover aktuell sm periode. ",
          "tiltakAndre": null
        },
        "meldingTilNav": {
          "navBoerTaTakISaken": false,
          "navBoerTaTakISakenBegrunnelse": null
        },
        "innspillTilArbeidsgiver": null,
        "tilbakedatering": {
          "dokumenterbarPasientkontakt": null,
          "tilbakedatertBegrunnelse": null
        },
        "bekreftelse": {
          "utstedelsesdato": "2018-10-09",
          "sykmelder": "Helen Flood",
          "sykmelderTlf": "113"
        }
      },
      {
        "id": "0ba8ea3e-2bd1-4d03-b127-40a5535fcf93",
        "startLegemeldtFravaer": "2018-10-09",
        "skalViseSkravertFelt": true,
        "identdato": "2018-10-09",
        "status": "NY",
        "naermesteLederStatus": null,
        "innsendtArbeidsgivernavn": null,
        "valgtArbeidssituasjon": null,
        "mottakendeArbeidsgiver": null,
        "orgnummer": null,
        "sendtdato": null,
        "sporsmal": null,
        "pasient": {
          "fnr": "110110110110",
          "fornavn": "Helen",
          "mellomnavn": "Perma",
          "etternavn": "Flood"
        },
        "arbeidsgiver": "PONTYPANDY FIRE SERVICE",
        "stillingsprosent": 100,
        "diagnose": {
          "hoveddiagnose": {
            "diagnose": "TENDINITT INA",
            "diagnosekode": "L87",
            "diagnosesystem": "ICPC-2"
          },
          "bidiagnoser": [
            {
              "diagnose": "GANGLION SENE",
              "diagnosekode": "L87",
              "diagnosesystem": "ICPC-2"
            }
          ],
          "fravaersgrunnLovfestet": null,
          "fravaerBeskrivelse": "Medising årsak i kategorien annet",
          "svangerskap": true,
          "yrkesskade": true,
          "yrkesskadeDato": "2018-10-09"
        },
        "mulighetForArbeid": {
          "perioder": [
            {
              "fom": "2018-10-09",
              "tom": "2018-10-17",
              "grad": 100,
              "behandlingsdager": null,
              "reisetilskudd": null,
              "avventende": null
            }
          ],
          "aktivitetIkkeMulig433": [
            "Annet"
          ],
          "aktivitetIkkeMulig434": [
            "Annet"
          ],
          "aarsakAktivitetIkkeMulig433": "andre årsaker til sykefravær",
          "aarsakAktivitetIkkeMulig434": "andre årsaker til sykefravær"
        },
        "friskmelding": {
          "arbeidsfoerEtterPerioden": true,
          "hensynPaaArbeidsplassen": "Må ta det pent",
          "antarReturSammeArbeidsgiver": true,
          "antattDatoReturSammeArbeidsgiver": "2018-10-09",
          "antarReturAnnenArbeidsgiver": true,
          "tilbakemeldingReturArbeid": "2018-10-09",
          "utenArbeidsgiverAntarTilbakeIArbeid": false,
          "utenArbeidsgiverAntarTilbakeIArbeidDato": null,
          "utenArbeidsgiverTilbakemelding": null
        },
        "utdypendeOpplysninger": {
          "sykehistorie": "Langvarig korsryggsmerter. Ømhet og smerte",
          "paavirkningArbeidsevne": "Kan ikke utføre arbeidsoppgaver 100% som kreves fra yrket",
          "resultatAvBehandling": "Nei",
          "henvisningUtredningBehandling": "Henvist til fysio",
          "grupper": [
            {
              "id": "6.2",
              "sporsmal": [
                {
                  "id": "6.2.1",
                  "svar": "Langvarig korsryggsmerter. Ømhet og smerte"
                },
                {
                  "id": "6.2.2",
                  "svar": "Kan ikke utføre arbeidsoppgaver 100% som kreves fra yrket"
                },
                {
                  "id": "6.2.3",
                  "svar": "Nei"
                },
                {
                  "id": "6.2.4",
                  "svar": "Henvist til fysio"
                }
              ]
            }
          ]
        },
        "arbeidsevne": {
          "tilretteleggingArbeidsplass": "Fortsett som sist.",
          "tiltakNAV": "Pasienten har plager som er kommet tilbake etter operasjon. Det er nylig tatt MR bildet som viser forandringer i hånd som mulig må opereres. Venter på time. Det er mulig sykemledingen vil vare utover aktuell sm periode. ",
          "tiltakAndre": null
        },
        "meldingTilNav": {
          "navBoerTaTakISaken": false,
          "navBoerTaTakISakenBegrunnelse": null
        },
        "innspillTilArbeidsgiver": null,
        "tilbakedatering": {
          "dokumenterbarPasientkontakt": null,
          "tilbakedatertBegrunnelse": null
        },
        "bekreftelse": {
          "utstedelsesdato": "2018-10-09",
          "sykmelder": "Helen Flood",
          "sykmelderTlf": "113"
        }
      }
    ],
    "hendelser": [
      {
        "id": null,
        "inntruffetdato": "2018-10-18T00:00:00",
        "type": "NY_NAERMESTE_LEDER",
        "antallDager": null,
        "tekstkey": "tidslinje.ny-naermeste-leder",
        "data": {
          "naermesteLeder": {
            "aktoerId": "1101101101102",
            "navn": "Station Officer Steele",
            "epost": "steele@pontypandyfire.gov.uk",
            "mobil": "110",
            "orgnummer": "110110110",
            "organisasjonsnavn": "PONTYPANDY FIRE SERVICE",
            "aktivTom": null,
            "arbeidsgiverForskuttererLoenn": true
          }
        }
      }
    ],
    "oppfoelgingsdato": "2018-08-23"
  }
]
